32a8/divM.v
//-- Entrada: clk_in. Señal original
//-- Salida: clk_out. Señal de frecuencia 1/M de la original
module divM(input wire clk_in, output wire clk_out);

//-- Valor por defecto del divisor
//-- Como en la iCEstick el reloj es de 100MHz, ponermos un valor de 4
//-- para obtener una frecuencia de salida de 250MHz
parameter M = 4;

//-- Numero de bits para almacenar el divisor
//-- Se calculan con la funcion de verilog $clog2, que nos devuelve el 
//-- numero de bits necesarios para representar el numero M
//-- Es un parametro local, que no se puede modificar al instanciar
localparam N = $clog2(M);

//-- Registro para implementar el contador modulo M
reg [N-1:0] divcounter = 0;

//-- Contador módulo M
always @(posedge clk_in)
  if (divcounter == M - 1) 
    divcounter <= 0;
  else 
    divcounter <= divcounter + 1;

//-- Sacar el bit mas significativo por clk_out
assign clk_out = divcounter[N-1];

endmodule

32a8/divM_tb.v
module divM_tb();

//-- Registro para generar la señal de reloj
reg clk = 0;
wire clk_out;


//-- Instanciar el componente y establecer el valor del divisor
divM #(4)
  dut(
    .clk_in(clk),
    .clk_out(clk_out)
  );

//-- Generador de reloj. Periodo 2 unidades
always #1 clk = ~clk;


//-- Proceso al inicio
initial begin

  //-- Fichero donde almacenar los resultados
  $dumpfile("divM_tb.vcd");
  $dumpvars(0, divM_tb);

  # 30 $display("FIN de la simulacion");
  $finish;
end

endmodule

32a8/divM_tb.vcd
$date
	Sun Sep 24 22:04:31 2017
$end
$version
	Icarus Verilog
$end
$timescale
	1s
$end
$scope module divM_tb $end
$var wire 1 ! clk_out $end
$var reg 1 " clk $end
$scope module dut $end
$var wire 1 " clk_in $end
$var wire 1 ! clk_out $end
$var reg 2 # divcounter [1:0] $end
$upscope $end
$upscope $end
$enddefinitions $end
#0
$dumpvars
b0 #
0"
0!
$end
#1
b1 #
1"
#2
0"
#3
1!
b10 #
1"
#4
0"
#5
b11 #
1"
#6
0"
#7
0!
b0 #
1"
#8
0"
#9
b1 #
1"
#10
0"
#11
1!
b10 #
1"
#12
0"
#13
b11 #
1"
#14
0"
#15
0!
b0 #
1"
#16
0"
#17
b1 #
1"
#18
0"
#19
1!
b10 #
1"
#20
0"
#21
b11 #
1"
#22
0"
#23
0!
b0 #
1"
#24
0"
#25
b1 #
1"
#26
0"
#27
1!
b10 #
1"
#28
0"
#29
b11 #
1"
