library.v
`timescale 1ns/1ps
//=============================================================================
//=============================================================================
module nand_cell (oNand, iA, iB);

  output                        oNand;
  input                         iA, iB;

  nand #(20:27:30) G1(oNand,iA,iB);

  specify
    specparam t_rise = 6;
    specparam t_fall = 6;

    (iA => oNand) = (t_rise, t_fall);
    (iB => oNand) = (t_rise, t_fall);
  endspecify


endmodule // nand
//=============================================================================
//=============================================================================
module nor_cell (oNor, iA, iB);

  output                        oNor;
  input                         iA, iB;

  nor #(20:27:30) G1(oNor,iA,iB);

  specify
    specparam t_rise = 6;
    specparam t_fall = 6;

    (iA => oNor) = (t_rise, t_fall);
    (iB => oNor) = (t_rise, t_fall);
  endspecify


endmodule // nor
//=============================================================================
//=============================================================================
module not_cell (oNot, iA);

  output                        oNot;
  input                         iA;

  not #(20:24:30) G1(oNot,iA);

  specify
    specparam t_rise = 6;
    specparam t_fall = 6;

    (iA => oNor) = (t_rise, t_fall);
  endspecify

endmodule // not
//=============================================================================
//=============================================================================
module mux (oMux, iA, iB, iSel, iEnb);

  output reg                    oMux;
  input wire                        iA, iB, iSel, iEnb;

  specify
    specparam t_rise = 6;
    specparam t_fall = 6;

    (iA => oMux) = (t_rise, t_fall);
    (iB => oMux) = (t_rise, t_fall);
    (iSel => oMux) = (t_rise, t_fall);
    (iEnb => oMux) = (t_rise, t_fall);
  endspecify

  always @ ( * ) begin
    if (~iEnb) begin
      case (iSel)
        1'b0:
        begin
          #(11:21:27) oMux <= iA;
        end
        1'b1:
        begin
          #(11:21:27) oMux <= iB;
        end
        default:
        begin
          #(11:21:27) oMux <= 1'b0;
        end
      endcase
    end else begin
      #(11:21:27) oMux <= 1'b0;
    end
  end

endmodule
//=============================================================================
//=============================================================================
module ffd (iClr, iPre, iClk, iD, oQp, oQn);

  output reg                oQp, oQn;
  input wire                iClr, iPre, iClk, iD;

  always @ ( posedge iClk ) begin
    if (iClr) begin
      case ({iPre})
        1'b0:
        begin
          #(10:15:30) oQp <= 1'b0;
          #(10:15:30) oQn <= 1'b1;
        end
        1'b1:
        begin
          #(10:15:30) oQp <= iD;
          #(10:15:30) oQn <= ~iD;
        end
        default:
        begin
          #(10:15:30) oQp <= oQp;
          #(10:15:30) oQn <= oQn;
        end
      endcase
    end else begin
      #(10:15:30) oQp <= 1'b0;
      #(10:15:30) oQn <= 1'b1;
    end
  end

  specify
    specparam t_rise = 6;
    specparam t_fall = 6;
    specparam t_setup_iD_iClk = 25;
    specparam t_hold_iD_iClk = 25;
    specparam t_width_l_iClk = 17;
    specparam t_width_h_iClk = 17;

    (posedge iClk *> (oQp +: iD)) = (t_rise, t_fall);
    (posedge iClk *> (oQn -: iD)) = (t_rise, t_fall);

    $setuphold(posedge iClk, posedge iD, t_setup_iD_iClk,t_hold_iD_iClk);
    $setuphold(posedge iClk, negedge iD, t_setup_iD_iClk,t_hold_iD_iClk);

    $width(posedge iClk, t_width_h_iClk, 0);
    $width(negedge iClk, t_width_l_iClk, 0);


  endspecify

endmodule // ffd

//=============================================================================
//=============================================================================

library_tester.v
module tester (oA, oB, oD, oClk, oEnb, oClr, oSel, oPre);

  output reg oA, oB, oD, oClk, oEnb, oClr, oSel, oPre;
  // Pruebas sincrónicas
  // Reloj
  initial begin
    oClk = 1'b0;
    oEnb = 1'b1;
    oClr = 1'b0;
    oSel = 1'b0;
    oPre = 1'b0;
    repeat(4) #35 oClk = ~oClk;
    oEnb = 1'b0;
    oClr = 1'b1;
    oPre = 1'b1;
    forever #35 oClk = ~oClk;
  end

  initial begin
    @(negedge oEnb);
    oSel = 1'b1;
    oD = 1'b1;
    oA = 1'b0;
    oB = 1'b0;
    repeat(3) @(posedge oClk);
    oSel = 1'b0;
    oD = 1'b0;
    oA = 1'b0;
    oB = 1'b1;
    repeat(3) @(posedge oClk);
    oSel = 1'b0;
    oD = 1'b1;
    oA = 1'b1;
    oB = 1'b0;
    repeat(3) @(posedge oClk);
    oSel = 1'b1;
    oD = 1'b0;
    oA = 1'b1;
    oB = 1'b1;
    repeat(3) @(posedge oClk);
    oSel = 1'b0;
    oD = 1'b1;
    oA = 1'b0;
    oB = 1'b0;
    repeat(3) @(posedge oClk);
    oSel = 1'b1;
    oD = 1'b0;
    oA = 1'b0;
    oB = 1'b1;
    repeat(3) @(posedge oClk);
    oSel = 1'b0;
    oD = 1'b0;
    oA = 1'b1;
    oB = 1'b0;
    repeat(3) @(posedge oClk);
    oSel = 1'b1;
    oD = 1'b1;
    oA = 1'b1;
    oB = 1'b1;
    repeat(3) @(posedge oClk);
    $finish;
  end

  initial begin
    $dumpfile ("library.vcd");
//    $dumpvars(1, library_tb);
    $dumpvars;
  end

endmodule // tester

library_tb.v
`timescale 1ns/1ps
`include "library.v"
`include "library_tester.v"
module test_bench ();

  wire Nand, Nor, Not, Mux, Qn, Qp;

  tester tester00(
    oA, oB, oD, oClk, oEnb, oClr, oSel, oPre
  );

  nand_cell nand00
  (
    .oNand(Nand),
    .iA(oA),
    .iB(oB)
  );

  nor_cell nor00
  (
    .oNor(Nor),
    .iA(oA),
    .iB(oB)
  );

  not_cell not00
  (
    .oNot(Not),
    .iA(oA)
  );

  mux mux00
  (
    .oMux(Mux),
    .iA(oA),
    .iB(oB),
    .iSel(oSel),
    .iEnb(oEnb)
  );

  ffd ffd00
  (
    .iClr(oClr),
    .iPre(oPre),
    .iClk(oClk),
    .iD(oD),
    .oQp(Qp),
    .oQn(Qn)
  );

endmodule // test_bench

library.vcd
$date
	Sun Sep 10 12:51:49 2017
$end
$version
	Icarus Verilog
$end
$timescale
	1ps
$end
$scope module test_bench $end
$var wire 1 ! Mux $end
$var wire 1 " Nand $end
$var wire 1 # Nor $end
$var wire 1 $ Not $end
$var wire 1 % Qn $end
$var wire 1 & Qp $end
$var wire 1 ' oA $end
$var wire 1 ( oB $end
$var wire 1 ) oClk $end
$var wire 1 * oClr $end
$var wire 1 + oD $end
$var wire 1 , oEnb $end
$var wire 1 - oPre $end
$var wire 1 . oSel $end
$scope module tester00 $end
$var reg 1 / oA $end
$var reg 1 0 oB $end
$var reg 1 1 oClk $end
$var reg 1 2 oClr $end
$var reg 1 3 oD $end
$var reg 1 4 oEnb $end
$var reg 1 5 oPre $end
$var reg 1 6 oSel $end
$upscope $end
$scope module nand00 $end
$var wire 1 ' iA $end
$var wire 1 ( iB $end
$var wire 1 " oNand $end
$upscope $end
$scope module nor00 $end
$var wire 1 ' iA $end
$var wire 1 ( iB $end
$var wire 1 # oNor $end
$upscope $end
$scope module not00 $end
$var wire 1 ' iA $end
$var wire 1 $ oNot $end
$upscope $end
$scope module mux00 $end
$var wire 1 ' iA $end
$var wire 1 ( iB $end
$var wire 1 , iEnb $end
$var wire 1 . iSel $end
$var reg 1 7 oMux $end
$upscope $end
$scope module ffd00 $end
$var wire 1 ) iClk $end
$var wire 1 * iClr $end
$var wire 1 + iD $end
$var wire 1 - iPre $end
$var reg 1 8 oQn $end
$var reg 1 9 oQp $end
$upscope $end
$upscope $end
$enddefinitions $end
#0
$dumpvars
x9
x8
x7
06
05
14
x3
02
01
x0
x/
0.
0-
1,
x+
0*
0)
x(
x'
x&
x%
x$
x#
x"
x!
$end
#27000
07
0!
#35000
11
1)
#65000
09
0&
#70000
01
0)
#95000
18
1%
#105000
11
1)
#140000
00
0(
0/
0'
13
1+
16
1.
15
1-
12
1*
04
0,
01
0)
#170000
1"
1#
1$
#175000
11
1)
#205000
19
1&
#210000
01
0)
#235000
08
0%
#245000
11
1)
#280000
01
0)
#315000
10
1(
03
0+
06
0.
11
1)
#345000
09
0&
0#
#350000
01
0)
#375000
18
1%
#385000
11
1)
#420000
01
0)
#455000
11
1)
#490000
01
0)
#525000
00
0(
1/
1'
13
1+
11
1)
#552000
17
1!
#555000
19
1&
0$
#560000
01
0)
#585000
08
0%
#595000
11
1)
#630000
01
0)
#665000
11
1)
#700000
01
0)
#735000
10
1(
03
0+
16
1.
11
1)
#765000
09
0&
0"
#770000
01
0)
#795000
18
1%
#805000
11
1)
#840000
01
0)
#875000
11
1)
#910000
01
0)
#945000
00
0(
0/
0'
13
1+
06
0.
11
1)
#972000
07
0!
#975000
19
1&
1"
1#
1$
#980000
01
0)
#1005000
08
0%
#1015000
11
1)
#1050000
01
0)
#1085000
11
1)
#1120000
01
0)
#1155000
10
1(
03
0+
16
1.
11
1)
#1182000
17
1!
#1185000
09
0&
0#
#1190000
01
0)
#1215000
18
1%
#1225000
11
1)
#1260000
01
0)
#1295000
11
1)
#1330000
01
0)
#1365000
00
0(
1/
1'
06
0.
11
1)
#1395000
0$
#1400000
01
0)
#1435000
11
1)
#1470000
01
0)
#1505000
11
1)
#1540000
01
0)
#1575000
10
1(
13
1+
16
1.
11
1)
#1605000
19
1&
0"
#1610000
01
0)
#1635000
08
0%
