piso/parallelinput_serialoutput.v
// Código en verilog para el segmento de conversión de 
// entrada en paralelo - salida en serie del bloque de 
// transmisición de la capa física de la pcie

module piso(clk, load, parallel_in, int_re, serial_ou);

input clk, load;         //clk:reloj; load:señal de carga
input [0:9] parallel_in; //entrada en paralelo
output [0:9] int_re;    //registro interno de la entrada   
output serial_ou;        //salida en serie

reg [0:9] int_re; 
assign serial_ou = int_re[9]; //pasa el registro interno a la salida 
                               //en serie    
always @ (posedge clk) //convierte la entrada en paralelo a serie
begin
   int_re[0] <= ((load && parallel_in[0]) || (~load && 1'b0));
   int_re[1] <= ((load && parallel_in[1]) || (~load && int_re[0]));
   int_re[2] <= ((load && parallel_in[2]) || (~load && int_re[1]));
   int_re[3] <= ((load && parallel_in[3]) || (~load && int_re[2]));
   int_re[4] <= ((load && parallel_in[4]) || (~load && int_re[3]));
   int_re[5] <= ((load && parallel_in[5]) || (~load && int_re[4]));
   int_re[6] <= ((load && parallel_in[6]) || (~load && int_re[5]));
   int_re[7] <= ((load && parallel_in[7]) || (~load && int_re[6]));
   int_re[8] <= ((load && parallel_in[8]) || (~load && int_re[7]));
   int_re[9] <= ((load && parallel_in[9]) || (~load && int_re[8]));
end

endmodule

piso/parallelinput_serialoutput_tb.v
//test bench para el segmento parallelinput_serialoutput.v

module piso_tb;
reg clk, load;
reg [0:9] parallel_in;
wire [0:9] int_re;
wire serial_ou;
initial		//define clock
begin
   clk = 1'b0;
   forever
      #10 clk = ~clk;
end

initial
$monitor ("load=%b, parallel_in=%b, int_re=%b, serial_ou=%b", load, parallel_in, int_re, serial_ou);

initial 		  //apply input vectors
begin

$dumpfile("parallelinput_serialoutput_prueba.vcd");
$dumpvars;

  #0  load = 1'b0; parallel_in = 10'b0000000000;
  #5  load = 1'b1; parallel_in = 10'b0101010101;
  #10 load = 1'b0;
  #30 load = 1'b1; parallel_in = 10'b1100110011;
  #20 load = 1'b0;
  #10 load = 1'b1; parallel_in = 10'b1111111111;
  #10 load = 1'b0;
  #20 load = 1'b1; parallel_in = 10'b1111111111;
  #10 load = 1'b0;
  #30 load = 1'b1; parallel_in = 10'b1100110011;
  #20 load = 1'b0;
  #10 load = 1'b1; parallel_in = 10'b1111111111;
  #10 load = 1'b0;
  #20 load = 1'b1; parallel_in = 10'b1111111111;
  #10 load = 1'b0;
  #30 load = 1'b1; parallel_in = 10'b1100110011;
  #20 load = 1'b0;
  #10 load = 1'b1; parallel_in = 10'b1111111111;
  #10 load = 1'b0;
  #20 load = 1'b1; parallel_in = 10'b1111111111;
  #10 load = 1'b0;
  #30 $stop;
end
piso inst_piso (	 //instancia el modulo piso en 
                         //parallelinput_serialoutput.v
   .clk(clk),
   .load(load),
   .parallel_in(parallel_in),
   .int_re(int_re),
   .serial_ou(serial_ou)
   );
endmodule

piso/parallelinput_serialoutput_prueba.vcd
$date
	Sun Oct  8 23:36:55 2017
$end
$version
	Icarus Verilog
$end
$timescale
	1s
$end
$scope module piso_tb $end
$var wire 1 ! serial_ou $end
$var wire 10 " int_re [0:9] $end
$var reg 1 # clk $end
$var reg 1 $ load $end
$var reg 10 % parallel_in [0:9] $end
$scope module inst_piso $end
$var wire 1 # clk $end
$var wire 1 $ load $end
$var wire 10 & parallel_in [0:9] $end
$var wire 1 ! serial_ou $end
$var reg 10 ' int_re [0:9] $end
$upscope $end
$upscope $end
$enddefinitions $end
#0
$dumpvars
bx '
b0 &
b0 %
0$
0#
bx "
x!
$end
#5
b101010101 %
b101010101 &
1$
#10
1!
b101010101 "
b101010101 '
1#
#15
0$
#20
0#
#30
0!
b10101010 "
b10101010 '
1#
#40
0#
#45
b1100110011 %
b1100110011 &
1$
#50
1!
b1100110011 "
b1100110011 '
1#
#60
0#
#65
0$
#70
b110011001 "
b110011001 '
1#
#75
b1111111111 %
b1111111111 &
1$
#80
0#
#85
0$
#90
0!
b11001100 "
b11001100 '
1#
#100
0#
#105
1$
#110
1!
b1111111111 "
b1111111111 '
1#
#115
0$
#120
0#
#130
b111111111 "
b111111111 '
1#
#140
0#
#145
b1100110011 %
b1100110011 &
1$
#150
b1100110011 "
b1100110011 '
1#
#160
0#
#165
0$
#170
b110011001 "
b110011001 '
1#
#175
b1111111111 %
b1111111111 &
1$
#180
0#
#185
0$
#190
0!
b11001100 "
b11001100 '
1#
#200
0#
#205
1$
#210
1!
b1111111111 "
b1111111111 '
1#
#215
0$
#220
0#
#230
b111111111 "
b111111111 '
1#
#240
0#
#245
b1100110011 %
b1100110011 &
1$
#250
b1100110011 "
b1100110011 '
1#
#260
0#
#265
0$
#270
b110011001 "
b110011001 '
1#
#275
b1111111111 %
b1111111111 &
1$
#280
0#
#285
0$
#290
0!
b11001100 "
b11001100 '
1#
#300
0#
#305
1$
#310
1!
b1111111111 "
b1111111111 '
1#
#315
0$
#320
0#
#330
b111111111 "
b111111111 '
1#
